SolAster
examples
source
tools
