Metadata-Version: 1.0
Name: SolAster
Version: 1.0.6
Summary: Python package to calculate 'Sun-as-a-star' RVs.
Home-page: https://github.com/tamarervin/SolAster
Author: Tamar Ervin
Author-email: tamarervin@gmail.com
License: Apache Software License
Platform: UNKNOWN
